rezka_scraper/__init__.py
rezka_scraper/rezka_scraper.py
test/__init__.py
test/test_rezka_scraper.py
rezka_scraper-0.1.1.dist-info/LICENSE
rezka_scraper-0.1.1.dist-info/METADATA
rezka_scraper-0.1.1.dist-info/WHEEL
rezka_scraper-0.1.1.dist-info/top_level.txt
rezka_scraper-0.1.1.dist-info/RECORD
