Metadata-Version: 2.2
Name: rezka_scraper
Version: 0.1.1
Summary: RezkaScraper — это мини библиотека на Python для асинхронного поиска контента (аниме, фильмов, сериалов и мультфильмов) на сайте Rezka.ag
Home-page: https://github.com/OFFpolice/rezka_scraper
Author: OFFpolice
Author-email: offpolice2077@gmail.com
Classifier: Programming Language :: Python :: 3.10
Classifier: Programming Language :: Python :: 3.11
Classifier: License :: OSI Approved :: MIT License
Classifier: Operating System :: OS Independent
Requires-Python: >=3.10
License-File: LICENSE
Requires-Dist: aiohttp==3.8.6
Requires-Dist: beautifulsoup4==4.12.3
Requires-Dist: fake-useragent==2.0.3
Dynamic: author
Dynamic: author-email
Dynamic: classifier
Dynamic: description
Dynamic: description-content-type
Dynamic: home-page
Dynamic: requires-dist
Dynamic: requires-python
Dynamic: summary
